imouse/__init__.py
imouse/types.py
imouse/api/__init__.py
imouse/api/client.py
imouse/api/config.py
imouse/api/device.py
imouse/api/event_dispatcher.py
imouse/api/mouse_key.py
imouse/api/payload.py
imouse/api/pic.py
imouse/api/shortcut.py
imouse/api/user.py
imouse/helper/__init__.py
imouse/helper/console/__init__.py
imouse/helper/console/airplay.py
imouse/helper/console/device.py
imouse/helper/console/group.py
imouse/helper/console/im_config.py
imouse/helper/console/usb.py
imouse/helper/console/user.py
imouse/helper/device/__init__.py
imouse/helper/device/image.py
imouse/helper/device/keyboard.py
imouse/helper/device/mouse.py
imouse/helper/device/shortcut.py
imouse/models/__init__.py
imouse/models/response.py
imouse/utils/__init__.py
imouse/utils/logger.py
imouse/utils/utils.py
imouse_py-0.0.4.dist-info/METADATA
imouse_py-0.0.4.dist-info/WHEEL
imouse_py-0.0.4.dist-info/top_level.txt
imouse_py-0.0.4.dist-info/RECORD
