Metadata-Version: 2.1
Name: imouse-py
Version: 0.0.4
Summary: iMouse设备自动化控制库一个基于客户端-服务端架构的Python库,用于自动化控制iOS设备
Home-page: https://github.com/iosauto/imouse-py
Author: iMouse
Author-email: your_email@example.com
Classifier: Programming Language :: Python :: 3
Classifier: License :: OSI Approved :: MIT License
Classifier: Operating System :: OS Independent
Requires-Python: >=3.8
Requires-Dist: annotated-types >=0.7.0
Requires-Dist: certifi >=2025.7.9
Requires-Dist: charset-normalizer >=3.4.2
Requires-Dist: colorlog >=6.9.0
Requires-Dist: idna >=3.10
Requires-Dist: pydantic >=2.10.6
Requires-Dist: pydantic-core >=2.27.2
Requires-Dist: requests >=2.32.4
Requires-Dist: typing-extensions >=4.13.2
Requires-Dist: urllib3 >=2.2.3
Requires-Dist: websocket-client >=1.8.0
